mosaik_hdf5.py
mosaik.HDF5_SemVer-0.4.0rc20210917000526.dist-info/AUTHORS.txt
mosaik.HDF5_SemVer-0.4.0rc20210917000526.dist-info/LICENSE.txt
mosaik.HDF5_SemVer-0.4.0rc20210917000526.dist-info/METADATA
mosaik.HDF5_SemVer-0.4.0rc20210917000526.dist-info/WHEEL
mosaik.HDF5_SemVer-0.4.0rc20210917000526.dist-info/entry_points.txt
mosaik.HDF5_SemVer-0.4.0rc20210917000526.dist-info/top_level.txt
mosaik.HDF5_SemVer-0.4.0rc20210917000526.dist-info/RECORD
