Metadata-Version: 2.1
Name: mosaik.HDF5-SemVer
Version: 0.4.0rc20210917000526
Summary: Stores mosaik simulation data in an HDF5 database.
Home-page: https://bitbucket.org/mosaik/mosaik-hdf5
Author: Stefan Scherfke
Author-email: bengt.lueers@gmail.com
Maintainer: Bengt Lüers
Maintainer-email: bengt.lueers@gmail.com
License: UNKNOWN
Platform: UNKNOWN
Classifier: Development Status :: 4 - Beta
Classifier: Environment :: Console
Classifier: Intended Audience :: Science/Research
Classifier: License :: OSI Approved :: GNU Lesser General Public License v2 (LGPLv2)
Classifier: Natural Language :: English
Classifier: Operating System :: OS Independent
Classifier: Programming Language :: Python
Classifier: Programming Language :: Python :: 3
Classifier: Programming Language :: Python :: 3.7
Classifier: Programming Language :: Python :: 3.8
Classifier: Programming Language :: Python :: 3.9
Classifier: Topic :: Scientific/Engineering
Requires-Dist: h5py (>=2.2.1)
Requires-Dist: mosaik.API-SemVer (>=2.4.2rc20201202043229)
Requires-Dist: networkx (>=1.9)
Requires-Dist: numpy (>=1.8.1)
